pyCFS/__init__.py
pyCFS/py.typed
pyCFS/pyCFS.py
pyCFS/application/__init__.py
pyCFS/application/acoustic/__init__.py
pyCFS/application/acoustic/placeholder.py
pyCFS/data/__init__.py
pyCFS/data/_v_def.py
pyCFS/data/util.py
pyCFS/data/extras/__init__.py
pyCFS/data/extras/ansys_io.py
pyCFS/data/extras/ansys_to_cfs_element_types.py
pyCFS/data/extras/cgns_io.py
pyCFS/data/extras/cgns_types.py
pyCFS/data/extras/ensight_io.py
pyCFS/data/extras/exodus_io.py
pyCFS/data/extras/exodus_to_cfs_element_types.py
pyCFS/data/extras/meshio_io.py
pyCFS/data/extras/nihu_io.py
pyCFS/data/extras/nihu_types.py
pyCFS/data/extras/psv_io.py
pyCFS/data/extras/stl_io.py
pyCFS/data/extras/vtk_types.py
pyCFS/data/io/_CFSArrayModule.py
pyCFS/data/io/_CFSMeshDataModule.py
pyCFS/data/io/_CFSReaderModule.py
pyCFS/data/io/_CFSRegDataModule.py
pyCFS/data/io/_CFSResultContainerModule.py
pyCFS/data/io/_CFSWriterModule.py
pyCFS/data/io/__init__.py
pyCFS/data/io/_simple.py
pyCFS/data/io/cfs_types.py
pyCFS/data/operators/__init__.py
pyCFS/data/operators/_nearest_neighbor_interpolation.py
pyCFS/data/operators/_projection_interpolation.py
pyCFS/data/operators/_rbf_interpolation.py
pyCFS/data/operators/derivatives.py
pyCFS/data/operators/dynamic_mode_decomposition.py
pyCFS/data/operators/field_fft.py
pyCFS/data/operators/interpolators.py
pyCFS/data/operators/modal_analysis.py
pyCFS/data/operators/sngr.py
pyCFS/data/operators/transformation.py
pyCFS/topt/__init__.py
pyCFS/topt/_param_functions.py
pyCFS/topt/topt.py
pyCFS/util/__init__.py
pyCFS/util/_update_pycfs_version.py
pyCFS/util/consts.py
pyCFS/util/lib_types.py
pyCFS/util/setup_generator.py
pyCFS/util/update_version.py
pyCFS/util/templates/config.yaml
pyCFS/util/templates/mat.xml
pyCFS/util/templates/run_sim.py
pyCFS/util/templates/sim.jou
pyCFS/util/templates/sim.xml
pyCFS/util/templates/sim_setup.py
pyCFS/util/templates/sim_setup_opti.py
pycfs-0.2.0.dist-info/LICENSE
pycfs-0.2.0.dist-info/METADATA
pycfs-0.2.0.dist-info/WHEEL
pycfs-0.2.0.dist-info/entry_points.txt
pycfs-0.2.0.dist-info/top_level.txt
pycfs-0.2.0.dist-info/RECORD
