Metadata-Version: 2.1
Name: pycfs
Version: 0.2.0
Summary: Python library for automating and data handling tasks for openCFS.
Author-email: IGTE <igte.gitlab@gmail.com>, Eniz Mušeljić <eniz.m@outlook.com>, Andreas Wurzinger <andreas.wurzinger@tugraz.at>, Patrick Heidegger <patrick.heidegger@tugraz.at>, Luca Candussi <luca.candussi@tugraz.at>
License: MIT License
Project-URL: Homepage, https://opencfs.org/
Project-URL: Documentation, https://opencfs.gitlab.io/pycfs/
Project-URL: Repository, https://gitlab.com/openCFS/pycfs
Project-URL: Issues, https://gitlab.com/openCFS/pycfs/-/issues
Project-URL: Changelog, https://gitlab.com/openCFS/pycfs/-/blob/main/Changelog.md
Keywords: automation,simulation,optimization,opencfs,data processing
Classifier: Development Status :: 4 - Beta
Classifier: Intended Audience :: Science/Research
Classifier: Topic :: Scientific/Engineering
Classifier: License :: OSI Approved :: MIT License
Classifier: Programming Language :: Python :: 3.10
Classifier: Programming Language :: Python :: 3.11
Classifier: Programming Language :: Python :: 3.12
Classifier: Programming Language :: Python :: 3.13
Classifier: Natural Language :: English
Requires-Python: >=3.10
License-File: LICENSE
Requires-Dist: numpy ==2.1.3
Requires-Dist: matplotlib ==3.10.7
Requires-Dist: typing ==3.7.4.3
Requires-Dist: typed-argument-parser ==1.9.0
Requires-Dist: tqdm ==4.66.2
Requires-Dist: h5py ==3.15.1
Requires-Dist: numba ==0.62.1
Requires-Dist: netCDF4 >=1.7.2
Requires-Dist: scipy >=1.10.1
Requires-Dist: scikit-spatial >=7.0.0
Requires-Dist: pyuff ==2.1
Requires-Dist: stl-reader ==0.2.2
Provides-Extra: all
Requires-Dist: vtk >=9.3.0 ; extra == 'all'
Requires-Dist: ansys-dpf-core >=0.10.0 ; extra == 'all'
Requires-Dist: pyvista >=0.43.1 ; extra == 'all'
Requires-Dist: pydmd >=2025.6.1 ; extra == 'all'
Requires-Dist: meshio >=5.0.0 ; extra == 'all'
Provides-Extra: ansys
Requires-Dist: ansys-dpf-core >=0.10.0 ; extra == 'ansys'
Requires-Dist: pyvista >=0.43.1 ; extra == 'ansys'
Provides-Extra: dev
Requires-Dist: sphinx ==7.2.6 ; extra == 'dev'
Requires-Dist: myst-parser ==2.0.0 ; extra == 'dev'
Requires-Dist: sphinx-book-theme ==1.1.2 ; extra == 'dev'
Requires-Dist: pytest ==8.0.2 ; extra == 'dev'
Requires-Dist: pytest-cov ==4.1.0 ; extra == 'dev'
Requires-Dist: black ==24.2.0 ; extra == 'dev'
Requires-Dist: mypy ==1.8.0 ; extra == 'dev'
Requires-Dist: flake8 ==7.0.0 ; extra == 'dev'
Requires-Dist: twine ==5.0.0 ; extra == 'dev'
Requires-Dist: build ==1.1.1 ; extra == 'dev'
Requires-Dist: pandas >=2.0.3 ; extra == 'dev'
Provides-Extra: dmd
Requires-Dist: pydmd >=2025.6.1 ; extra == 'dmd'
Provides-Extra: meshio
Requires-Dist: meshio >=5.0.0 ; extra == 'meshio'
Provides-Extra: vtk
Requires-Dist: vtk >=9.3.0 ; extra == 'vtk'
